greet_aniketpy-0.1.0.dist-info/licenses/LICENSE
greetpy/__init__.py
greetpy/core.py
greet_aniketpy-0.1.0.dist-info/METADATA
greet_aniketpy-0.1.0.dist-info/WHEEL
greet_aniketpy-0.1.0.dist-info/entry_points.txt
greet_aniketpy-0.1.0.dist-info/top_level.txt
greet_aniketpy-0.1.0.dist-info/RECORD
